OurvleApi/__init__.py
OurvleApi/ourvle.py
OurvleApi-0.3.1.dist-info/LICENSE
OurvleApi-0.3.1.dist-info/METADATA
OurvleApi-0.3.1.dist-info/WHEEL
OurvleApi-0.3.1.dist-info/top_level.txt
OurvleApi-0.3.1.dist-info/RECORD
