Metadata-Version: 2.1
Name: OurvleApi
Version: 0.3.1
Summary: Unofficial module for Ourvle
Home-page: https://github.com/Alexcmad/OurvleScraper
Author: Alexander McIntosh
Author-email: mcintoshalexander80@gmail.com
Classifier: Programming Language :: Python :: 3
Classifier: License :: OSI Approved :: MIT License
Classifier: Operating System :: OS Independent
Requires-Python: >=3.7
License-File: LICENSE
Requires-Dist: beautifulsoup4 (==4.11.2)
Requires-Dist: requests (==2.28.1)
